edwh_bonnes_plugin/__about__.py
edwh_bonnes_plugin/__init__.py
edwh_bonnes_plugin/bonnes_plugin.py
edwh_bonnes_plugin-0.7.2.dist-info/METADATA
edwh_bonnes_plugin-0.7.2.dist-info/WHEEL
edwh_bonnes_plugin-0.7.2.dist-info/entry_points.txt
edwh_bonnes_plugin-0.7.2.dist-info/licenses/LICENSE.txt
edwh_bonnes_plugin-0.7.2.dist-info/RECORD
