Metadata-Version: 2.3
Name: edwh-bonnes-plugin
Version: 0.7.2
Summary: The greatest project to be created from the edwh package.
Project-URL: Documentation, https://github.com/educationwarehouse/edwh-bonnes-tasks-plugin#readme
Project-URL: Issues, https://github.com/educationwarehouse/edwh-bonnes-tasks-plugin/issues
Project-URL: Source, https://github.com/educationwarehouse/edwh-bonnes-tasks-plugin
Author-email: Remco Boerma <remco.b@educationwarehouse.nl>, Robin van der Noord <robin.vdn@educationwarehouse.nl>, Bonne Lueks <bonne.l@educationwarehouse.nl>
License-Expression: MIT
License-File: LICENSE.txt
Keywords: edwh
Classifier: Development Status :: 4 - Beta
Classifier: Programming Language :: Python
Classifier: Programming Language :: Python :: 3.10
Classifier: Programming Language :: Python :: 3.11
Classifier: Programming Language :: Python :: 3.12
Classifier: Programming Language :: Python :: Implementation :: CPython
Classifier: Programming Language :: Python :: Implementation :: PyPy
Requires-Python: >=3.10
Requires-Dist: edwh
Requires-Dist: pillow
Provides-Extra: dev
Requires-Dist: black; extra == 'dev'
Requires-Dist: hatch; extra == 'dev'
Requires-Dist: python-semantic-release<8; extra == 'dev'
